chip_tag_component/__init__.py
chip_tag_component/example.py
chip_tag_component/frontend/build/asset-manifest.json
chip_tag_component/frontend/build/bootstrap.min.css
chip_tag_component/frontend/build/index.html
chip_tag_component/frontend/build/static/css/main.bc289404.css
chip_tag_component/frontend/build/static/css/main.bc289404.css.map
chip_tag_component/frontend/build/static/js/main.d5bd613b.js
chip_tag_component/frontend/build/static/js/main.d5bd613b.js.LICENSE.txt
chip_tag_component/frontend/build/static/js/main.d5bd613b.js.map
streamlit_chip_tags-0.0.4.dist-info/LICENSE
streamlit_chip_tags-0.0.4.dist-info/METADATA
streamlit_chip_tags-0.0.4.dist-info/WHEEL
streamlit_chip_tags-0.0.4.dist-info/top_level.txt
streamlit_chip_tags-0.0.4.dist-info/RECORD
